werkflow_github/__init__.py
werkflow_github/github.py
werkflow_github/actions/__init__.py
werkflow_github/actions/common/__init__.py
werkflow_github/actions/common/models/__init__.py
werkflow_github/actions/common/models/conclusion.py
werkflow_github/actions/common/models/conclusion_map.py
werkflow_github/actions/common/models/status.py
werkflow_github/actions/common/models/status_map.py
werkflow_github/actions/jobs/__init__.py
werkflow_github/actions/jobs/models/__init__.py
werkflow_github/actions/jobs/models/job.py
werkflow_github/actions/jobs/models/job_validator.py
werkflow_github/actions/pull_requests/__init__.py
werkflow_github/actions/pull_requests/models/__init__.py
werkflow_github/actions/pull_requests/models/pull_request.py
werkflow_github/actions/pull_requests/models/pull_request_ref.py
werkflow_github/actions/pull_requests/models/pull_request_ref_validator.py
werkflow_github/actions/pull_requests/models/pull_request_validator.py
werkflow_github/actions/steps/__init__.py
werkflow_github/actions/steps/models/__init__.py
werkflow_github/actions/steps/models/step.py
werkflow_github/actions/steps/models/step_validator.py
werkflow_github/actions/workflows/__init__.py
werkflow_github/actions/workflows/models/__init__.py
werkflow_github/actions/workflows/models/actor_validator.py
werkflow_github/actions/workflows/models/test.py
werkflow_github/actions/workflows/models/workflow_validator.py
werkflow_github/exceptions/__init__.py
werkflow_github/exceptions/bad_request_error.py
werkflow_github/exceptions/method_not_allowed_error.py
werkflow_github/exceptions/resource_not_found_error.py
werkflow_github/exceptions/server_failed_error.py
werkflow_github/exceptions/unauthorized_request_error.py
werkflow_github/exceptions/unprocessable_content_error.py
werkflow_github/parsing/__init__.py
werkflow_github/parsing/get_next_page.py
werkflow_github/repos/__init__.py
werkflow_github/repos/models/__init__.py
werkflow_github/repos/models/repo.py
werkflow_github-0.2.2.dist-info/licenses/LICENSE
werkflow_github-0.2.2.dist-info/METADATA
werkflow_github-0.2.2.dist-info/WHEEL
werkflow_github-0.2.2.dist-info/top_level.txt
werkflow_github-0.2.2.dist-info/RECORD
